qrpca/__init__.py
qrpca/decomposition.py
qrpca-1.5.6.dist-info/LICENSE
qrpca-1.5.6.dist-info/METADATA
qrpca-1.5.6.dist-info/WHEEL
qrpca-1.5.6.dist-info/top_level.txt
qrpca-1.5.6.dist-info/RECORD
