Metadata-Version: 2.1
Name: qrpca
Version: 1.5.6
Summary: A Python package for QR based PCA decomposition with CUDA acceleration via torch.
Home-page: https://github.com/xuquanfeng/qrpca
Author: Xu Quanfeng
Author-email: xqf3520@163.com
Keywords: Astronomy data analysis,Astronomy toolbox,Dimensionality reduction
Classifier: Topic :: Scientific/Engineering
Classifier: License :: OSI Approved :: GNU Lesser General Public License v3 (LGPLv3)
Classifier: Programming Language :: Python :: 3
Requires-Python: >=3.6
License-File: LICENSE
